[
{"value":"1","label":"تایپ و تکثیر"},
{"value":"2","label":"آبکاران"},
{"value":"3","label":"آرایشگران و پیرایشگران زنانه"},
{"value":"4","label":"آرایشگران و پیرایش گران مردانه"},
{"value":"5","label":"آهنسازان"},
{"value":"6","label":"آهنکاران"},
{"value":"7","label":"آهنگران اتومبیل و صنعتگران اتومبیل"},
{"value":"8","label":"اتوسرویس، تعمیرگاه و پارکینگ"},
{"value":"9","label":"اوراق کنندگان اتومبیل"},
{"value":"10","label":"باطریسازان و باطری فروشان"},
{"value":"11","label":"فروشندگان آبمیوه و بستنی و فالوده"},
{"value":"12","label":"ابزار و یراق فروشان"},
{"value":"13","label":"اغذیه فروشان"},
{"value":"14","label":"آهن فروشان"},
{"value":"15","label":"بار فروشان میوه و تره بار"},
{"value":"16","label":"موسسات حمل و نقل کالا"},
{"value":"17","label":"بنکداران پارچه"},
{"value":"18","label":"عمده فروشان مواد غذایی"},
{"value":"19","label":"بوفه داران سینما و مجامع عمومی"},
{"value":"20","label":"پارچه فروشان"},
{"value":"21","label":"فروشندگان ماهی و پرنده"},
{"value":"22","label":"فروشندگان محصولات پلاستیکی"},
{"value":"23","label":"پیراهن دوزان و پیراهن فروشان"},
{"value":"24","label":"تابلوسازان و  تابلونویسان"},
{"value":"25","label":"تزیینات داخلی ساختمان"},
{"value":"26","label":"تشکدوزان اتومبیل"},
{"value":"27","label":"چاپخانه داران"},
{"value":"28","label":"چادردوزان و برزنت فروشان"},
{"value":"29","label":"وانت داران"},
{"value":"30","label":"تالارهای پذیرایی و ظروف کرایه"},
{"value":"31","label":"فروشندگان جراید"},
{"value":"32","label":"فروشندگان چرم و لوازم کفش"},
{"value":"33","label":"چوب بران وچوب فروشان"},
{"value":"34","label":"چلوکبابی ها و غذاخوری ( رستوران – تالارهای پذیرایی)"},
{"value":"35","label":"فروشندگان آجیل و خشکبار"},
{"value":"36","label":"خرازان"},
{"value":"37","label":"خواربار فروشان"},
{"value":"38","label":"فروشندگان دوچرخه و موتور سیکلت"},
{"value":"39","label":"فروشندگان دل، جگر و قلوه"},
{"value":"40","label":"رستوران ،سلف سرویس"},
{"value":"41","label":"فروشندگان رنگ"},
{"value":"42","label":"سمساران و امانت فروشان"},
{"value":"43","label":"دارندگان انبارهای کالاهای تجاری و بازرگانی و سردخانه"},
{"value":"44","label":"سوپر مارکت داران"},
{"value":"45","label":"شوفاژ کاران"},
{"value":"46","label":"فروشندگان و کرایه دهندگان چینی و بلور و لوستر"},
{"value":"47","label":"عطاران وسقط فروشان"},
{"value":"48","label":"فروشندگان غلات و حبوبات"},
{"value":"49","label":"تهیه کنندگان فتوکپی و اوزالید"},
{"value":"50","label":"فروشندگان فرش دستباف"},
{"value":"51","label":"فروشندگان فرش ماشینی و موکت"},
{"value":"52","label":"قهوه خانه داران"},
{"value":"53","label":"پزندگان ،‌کبابی و حلیم پزان"},
{"value":"54","label":"فروشندگان کاغذ و مقوا"},
{"value":"55","label":"لیست اتحادیه های تهران"},
{"value":"56","label":"طباخان و کله پزان"},
{"value":"57","label":"گل فروشان"},
{"value":"58","label":"گرمابه داران سونا و ماساژ"},
{"value":"59","label":"قصابان گاوی"},
{"value":"60","label":"قصابان گوسفندی"},
{"value":"61","label":"لوازم بهداشتی ساختمان"},
{"value":"62","label":"تهیه وتوزیع کنندگان تجهیزات ، لوازم پزشکی وآزمایشگاهی"},
{"value":"63","label":"فروشندگان لوازم طبی، آزمایشگاهی و دندانپزشکی"},
{"value":"64","label":"فروشندگان لوازم یدکی اتومبیل ( سبک و سنگین )"},
{"value":"65","label":"تولیدکنندگان و فروشندگان پوشاک"},
{"value":"66","label":"لبنیات ساز و لبنیات فروش"},
{"value":"67","label":"لیست اتحادیه های صنفی"},
{"value":"68","label":"لوازم فلزی خانگی و آشپزخانه"},
{"value":"69","label":"فروشندگان لوازم صوتی و تصویری"},
{"value":"70","label":"ماشین آلات کشاورزی"},
{"value":"71","label":"فروشندگان مصالح ساختمانی"},
{"value":"72","label":"فروشندگان میوه و تره بار"},
{"value":"73","label":"فروشندگان قفل و لولا"},
{"value":"74","label":"موسسات توریستی و اتومبیل کرایه"},
{"value":"75","label":"مسافرخانه داران و مهمانپذیران"},
{"value":"76","label":"موسسات حمل و نقل مسافر"},
{"value":"77","label":"لیست اصناف کشور"},
{"value":"78","label":"مشاورین املاک"},
{"value":"79","label":"مواد اولیه کشاورزی ولوازم باغبانی"},
{"value":"80","label":"فروشندگان اشیای قدیمی و صنایع دستی"},
{"value":"81","label":"کمپرسی داران و کامیون داران"},
{"value":"82","label":"فروشندگان نوشت افزار و لوازم مهندسی"},
{"value":"83","label":"نمایشگاهداران اتومبیل"},
{"value":"84","label":"فروشندگان لوازم خانگی"},
{"value":"85","label":"هتلداران"},
{"value":"86","label":"حلواساز و عصار"},
{"value":"87","label":"خشکشویی و لباسشویی"},
{"value":"88","label":"خیاطان"},
{"value":"89","label":"درود گران ، مبل سازان وکمد سازان"},
{"value":"90","label":"تعمیرکاران  موتور سیکلت و دوچرخه"},
{"value":"91","label":"ذوب فلزات"},
{"value":"92","label":"ساعت سازان و ساعت فروشان"},
{"value":"93","label":"سراجان"},
{"value":"94","label":"چراغ سازان و سماور"},
{"value":"95","label":"سنگ بر و سنگ تراش"},
{"value":"96","label":"شیشه بران و فروشندگان شیشه و آیینه"},
{"value":"97","label":"صباغ و گلزن"},
{"value":"98","label":"صحافان"},
{"value":"99","label":"فروشندگان و سازندگان طلا و جواهر و نقره"},
{"value":"100","label":"اتحادیه های صنفی"},
{"value":"101","label":"عکاسان و فیلمبرداران"},
{"value":"102","label":"فروشندگان و سازندگان عینک"},
{"value":"103","label":"فخاران"},
{"value":"104","label":"قالی شویان"},
{"value":"105","label":"قفل و کلید سازان"},
{"value":"106","label":"قنادان و شیرینی فروشان"},
{"value":"107","label":"کاشی ساز و کاشی فروش"},
{"value":"108","label":"تولیدکنندگان و فروشندگان کالای کشباف"},
{"value":"109","label":"کفاشان"},
{"value":"110","label":"تولید کنندگان کفشهای ماشینی و پلاستیکی"},
{"value":"111","label":"فروشندگان پوشاک"},
{"value":"112","label":"خواربار فروشان عطاران و سقط فروش"},
{"value":"113","label":"مشاورین املاک و نمایشگاه اتومبیل و تاکسی تلفنی"},
{"value":"114","label":"انواع اتحادیه ها"},
{"value":"115","label":"آهن و آلومینیوم، جوشکاران سیار، تانکرسازان و آهنگران"},
{"value":"116","label":"خواربار و لبنیات فروشان"},
{"value":"117","label":"تعمیر کاران و فروشنده لوازم یدکی و لاستیک فروشان"},
{"value":"118","label":"نانوایان"},
{"value":"119","label":"فروشندگان فرش و مصالح فرش"},
{"value":"120","label":"فروشندگان طلا و جواهر"},
{"value":"121","label":"درودگران و فلزکاران"},
{"value":"122","label":"کتابفروشان و خدمات کامپیوتری"},
{"value":"123","label":"تعمیر کاران اتومبیل ( سبک و سنگین )"},
{"value":"124","label":"فروشندگان لوله و لوازم بهداشتی ساختمانی"},
{"value":"125","label":"قنادان و بستنی ساز و بستنی فروش"},
{"value":"126","label":"ابزار و یراق و لوازم ایمنی و آتش نشانی"},
{"value":"127","label":"کباب پزان"},
{"value":"128","label":"خواربارفروشان، سوپرمارکت، لبنیات، مواد پروتیینی، قصاب و عطاری"},
{"value":"129","label":"آهنگران و درب و پنجره سازان آهنی"},
{"value":"130","label":"فروشندگان لوازم خانگی و صوتی و تصویری"},
{"value":"131","label":"طلا و جواهر، عکاسان، فیلمبرداران و ساعت فروشان"},
{"value":"132","label":"فروشندگان پوشاک و خرازان و لوازم بهداشتی و آرایشی"},
{"value":"133","label":"نانوایان، قنادان و علافان"},
{"value":"134","label":"فروشندگان و سازندگان طلا و جواهر ،عکاسان"},
{"value":"135","label":"قنادان و نانوایان"},
{"value":"136","label":"تعمیرکاران اتومبیل و تراشکار و دینام پیچ"},
{"value":"137","label":"مشاورین املاک و نمایشگاه داران اتومبیل"},
{"value":"138","label":"خدمات رایانه و عکاسان و طلا و جواهر فروشان"},
{"value":"139","label":"تعمیرگاه لوازم خانگی و اتومبیل"},
{"value":"140","label":"خواربارفروشان و لبنیات و مواد پروتیینی"},
{"value":"141","label":"تعمیر لوازم الکتریکی و الکترونیکی"},
{"value":"142","label":"حبوبات فروشان"},
{"value":"143","label":"فروشندگان و سازندگان طلا و جواهر و ساعت"},
{"value":"144","label":"دفاتر آژانسهای تاکسی تلفنی"},
{"value":"145","label":"فروشندگان کیف و کفش"},
{"value":"146","label":"شرکتهای خدماتی"},
{"value":"147","label":"فلزکاران"},
{"value":"148","label":"آرایشگران و زرگران"},
{"value":"149","label":"خواربارفروشان و علافان"},
{"value":"150","label":"فلزکاران، نجاران و موزاییک سازان"},
{"value":"151","label":"پارچه و پوشاک فروشان"},
{"value":"152","label":"لوازم خانگی و اغذیه فروشان"},
{"value":"153","label":"ابزار و مصالح ساختمانی و یدکی اتومبیل"},
{"value":"154","label":"خیاطان و عکاسان"},
{"value":"155","label":"درب وپنجره سازان ومصنوعات چوبی آهنی وآلومینیومی"},
{"value":"156","label":"فروشندگان پوشاک و خرازان"},
{"value":"157","label":"قصابان و هتلداران"},
{"value":"158","label":"کتابفروشان و عکاسان"},
{"value":"159","label":"آرایشگران و خیاطان بانوان و گلدوزی"},
{"value":"160","label":"خشکبار و دانه های روغنی و علافان"},
{"value":"161","label":"قنادان و قندریزان و نبات ریزان"},
{"value":"162","label":"مشاورین املاک، خودرو و حمل و نقل بار و مسافر"},
{"value":"163","label":"قهوه خانه داران و اغذیه فروشان - غذا خوری"},
{"value":"164","label":"خیاطان و آرایشگران"},
{"value":"165","label":"فروشندگان لاستیک و لوازم یدکی"},
{"value":"166","label":"فروشندگان کیف و کفش و پارچه"},
{"value":"167","label":"زرگران و آرایشگران مردانه"},
{"value":"168","label":"تولید کنندگان مصالح و خدمات ساختمانی"},
{"value":"169","label":"خرازان و کفش فروشان"},
{"value":"170","label":"آرایشگران مردانه و گرمابه داران"},
{"value":"171","label":"قصابان  و اغذیه فروشان"},
{"value":"172","label":"فروشندگان لوازم یدکی اتومبیل و بنگاه داران"},
{"value":"173","label":"ابزار و یراق و مصالح ساختمانی"},
{"value":"174","label":"دوردگران (‌نجاران )"},
{"value":"175","label":"موزاییک سازان"},
{"value":"176","label":"اغذیه فروشان و هتلداران"},
{"value":"177","label":"قصابان"},
{"value":"178","label":"کانال سازان  و حلبی سازان  و فلزکاران"},
{"value":"179","label":"خواربارفروشان، گندم و آرد فروشان"},
{"value":"180","label":"زرگران، عکاسان و کتابفروشان"},
{"value":"181","label":"الکتریکی و دوچرخه سازان"},
{"value":"182","label":"طلا سازان و طلا فروشان"},
{"value":"183","label":"لوازم یدکی اتومبیل و ادوات کشاورزی"},
{"value":"184","label":"خشکبار و حبوبات و بارفروشان"},
{"value":"185","label":"بافندگان فرش دستباف"},
{"value":"186","label":"مصالح ساختمانی و لوازم خانگی"},
{"value":"187","label":"تعمیر کاران اتومبیل  و فلزکاران"},
{"value":"188","label":"لوازم خانگی و کادویی"},
{"value":"189","label":"ساندویچ فروشان و بنگاه داران"},
{"value":"190","label":"خرازی، پوشاک، بزازان و کفاشان"},
{"value":"191","label":"تعمیرات لوازم برقی و شیشه بران"},
{"value":"192","label":"خیاطان و آرایشگران زنانه"},
{"value":"193","label":"تعمیرکاران و صافکاران اتومبیل"},
{"value":"194","label":"فروشندگان مرغ و تخم مرغ و مواد پروتینی"},
{"value":"195","label":"تعمیر کاران لوازم برقی و خانگی"},
{"value":"196","label":"بستنی ساز و بستنی فروش"},
{"value":"197","label":"صافکاران ، رادیاتورساز و گلگیرسازان"},
{"value":"198","label":"خیاطان مردانه"},
{"value":"199","label":"فروشندگان رنگ و ابزار و یراق"},
{"value":"200","label":"فروشندگان لوازم یدکی اتومبیل سنگین"},
{"value":"201","label":"تعمیرکاران و فروشندگان لوازم صوتی و تصویری"},
{"value":"202","label":"فروشندگان لاستیک"},
{"value":"203","label":"ادوات و نهاده های کشاورزی"},
{"value":"204","label":"مجازی"},
{"value":"205","label":"خرازان و تریکو"},
{"value":"206","label":"فروشندگان بلور، چینی و ابزار"},
{"value":"207","label":"تولید و فروش گز و شیرینی"},
{"value":"208","label":"فروشندگان کیف و کفش، پلاستیک و لوازم التحریر"},
{"value":"209","label":"آرایشگران و فروشندگان لوازم بهداشتی و آرایشی"},
{"value":"210","label":"درودگران و ابزار فروشان"},
{"value":"211","label":"خیاطان و کفاشان"},
{"value":"212","label":"نانوایان، آسیابداران و آرد فروشان"},
{"value":"213","label":"آرایشگران و پیرایشگران زنانه و مردانه"},
{"value":"214","label":"فروشندگان لوازم التحریر و کتاب فروشان"},
{"value":"215","label":"خواربارفروشان ،آجیل و خشکبار"},
{"value":"216","label":"خیاطان زنانه"},
{"value":"217","label":"خدمات رایانه ای"},
{"value":"218","label":"فروشندگان لوازم الکتریکی و الکترونیکی"},
{"value":"219","label":"عکاسان و چاپخانه داران"},
{"value":"220","label":"خیاطان و خشکشویی"},
{"value":"221","label":"درودگران وشیشه بران"},
{"value":"222","label":"موزاییک سازان و بلوک سازان"},
{"value":"223","label":"درودگران وبلوک سازان"},
{"value":"224","label":"لوازم خانگی و خرازی"},
{"value":"225","label":"ساندویچ فروشان و مسافرخانه داران"},
{"value":"226","label":"فروشنده مصالح ساختمانی و نمایشگاهداران و لوازم یدکی اتومبیل"},
{"value":"227","label":"فروشندگان و سازندگان طلا و جواهر و خیاطان"},
{"value":"228","label":"عکاسان و الکترونیک"},
{"value":"229","label":"قنادان ،‌نانوایان و بستنی"},
{"value":"230","label":"فروشندگان لوازم التحریر و خرازی"},
{"value":"231","label":"پزندگان، هتلداران و میوه وتره بار"},
{"value":"232","label":"بافندگان و تولیدکنندگان پوشاک"},
{"value":"233","label":"طلا فروشان، ساعت ساز و ساعت فروش، سمسار، گرمابه، آرایشگران مردانه و زنانه، خیاطان، تابلو نویس، خدمات رایانه ای"},
{"value":"234","label":"آهن فروشان و انبارهای کالاهای تجاری"},
{"value":"235","label":"فروشندگان لوازم الکتریکی و سیم کشی ساختمان"},
{"value":"236","label":"عکاسان، فیلمبرداران و خدمات رایانه"},
{"value":"237","label":"سراجان و کفاشان"},
{"value":"238","label":"صافکاران و نقاشان اتومبیل"},
{"value":"239","label":"تراشکاران"},
{"value":"240","label":"فروشندگان لوازم التحریر"},
{"value":"241","label":"عطاران"},
{"value":"242","label":"پنچرگیری و تعویض روغن"},
{"value":"243","label":"فروشندگان مرغ و تخم مرغ و ماهی"},
{"value":"244","label":"فروشندگان لوازم بهداشتی و لوازم پزشکی (طبی)"},
{"value":"245","label":"درب و پنجره سازان پروفیلی، اسکلت فلزی، داربست فلزی"},
{"value":"246","label":"نبات و آبنبات ریزان"},
{"value":"247","label":"فروشندگان میوه و تره بار و عمده فروش مواد غذایی"},
{"value":"248","label":"کتاب و لوازم التحریر فروشان و عکاسان"},
{"value":"249","label":"تاسیسات مکانیکی ساختمان"},
{"value":"250","label":"پروفیل کاران"},
{"value":"251","label":"باطریساز و برق کار اتومبیل"},
{"value":"252","label":"صنعت ساختمان"},
{"value":"253","label":"فروشندگان لاستیک ، پنچرگیری و تعویض روغن"},
{"value":"254","label":"نقاشان و اتو سرویس اتومبیل"},
{"value":"255","label":"اغذیه فروشان، کافه، رستوران"},
{"value":"256","label":"صنعتگران ( حلبی ساز - تراشکار - چراغساز )"},
{"value":"257","label":"تعمیرکاران و فروشندگان لوازم یدکی اتومبیل"},
{"value":"258","label":"فروشندگان و تعمیر کاران لوازم برقی"},
{"value":"259","label":"فروشندگان و سازندگان طلا و جواهر ، ساعت و عینک"},
{"value":"260","label":"قنادان  و آبنبات ریز و نقل ریزان"},
{"value":"261","label":"خدمات رایانه ، تابلو نویس، عکاسی و فیلمبردار"},
{"value":"262","label":"گرمابه داران، آرایشگران و خشکشویی"},
{"value":"263","label":"تعمیر کاران اتومبیل و تعمیرکاران  موتور سیکلت"},
{"value":"264","label":"رستوران، جگرکی، قهوه خانه داران و اغذیه فروشان"},
{"value":"265","label":"مصالح فروشان، لوازم بهداشتی ساختمان و ابزار و یراق"},
{"value":"266","label":"الکترونیک و تعمیرکاران لوازم برقی"},
{"value":"267","label":"تعمیرکاران و فروشندگان ساعت"},
{"value":"268","label":"تابلو نویسان و خطاطان"},
{"value":"269","label":"فروشندگان ابزار ساختمانی"},
{"value":"270","label":"لحاف، پشتی دوز، پتو و حوله فروش"},
{"value":"271","label":"پلاستیک و ملامین فروشان"},
{"value":"272","label":"فتوکپی و بنگاه های خدماتی"},
{"value":"273","label":"هتلداران، چلوکبابی، کبابی و جگرکی"},
{"value":"274","label":"فروشندگان لوازم  بهداشتی و آرایشی و خرازی"},
{"value":"275","label":"پارچه فروشان و خرازان"},
{"value":"276","label":"فروشندگان کیف وکفش  وپوشاک فروشان"},
{"value":"277","label":"سازندگان  و فروشندگان تانکر"},
{"value":"278","label":"تراشکاران و لنت کوبی"},
{"value":"279","label":"درودگران، جوشکاران، آلومینیوم کاران و کابینت سازان چوبی و فلزی"},
{"value":"280","label":"تعمیرکاران لوازم خانگی و سیم پیچ"},
{"value":"281","label":"خدمات خودرو"},
{"value":"282","label":"تراشکاران، تانکرسازان، آهنگران و ادوات کشاورزی"},
{"value":"283","label":"تعمیرکاران لوازم خانگی و نفتی و گازسوز"},
{"value":"284","label":"تعمیرکاران اتومبیل و پنچرگیری و تعویض روغن"},
{"value":"285","label":"لوازم خانگی و کتابفروشان"},
{"value":"286","label":"قصابان و لبنیات فروشان"},
{"value":"287","label":"فروشندگان پوشاک و خرازی و کفاشان و لوازم خانگی"},
{"value":"288","label":"مصالح ساختمانی و نخ و پشم قالی"},
{"value":"289","label":"تعمیرکاران لوازم برقی و تاسیسات"},
{"value":"290","label":"برقکار ، سیم کش و باطری ساز"},
{"value":"291","label":"جوشکاران، درب و پنجره سازان آهنی و آلومینیومی"},
{"value":"292","label":"فروشندگان لوازم یدکی اتومبیل و موتور سیکلت  و دوچرخه"},
{"value":"293","label":"فروشندگان لوازم خانگی و فرش و موکت"},
{"value":"294","label":"آلومینیوم سازان و تراشکاران"},
{"value":"295","label":"قصابان،وفروشندگان مرغ ، تخم مرغ و ماهی"},
{"value":"296","label":"الکتریکی و برق صنعتی"},
{"value":"297","label":"تعمیرکاران لوازم صوتی و تصویری"},
{"value":"298","label":"بلوک زنی و موزاییک سازان و مصالح ساختمانی"},
{"value":"299","label":"لوله کش و لوازم بهداشتی ساختمان"},
{"value":"300","label":"شیشه بران و فروشندگان شیشه و آیینه و رنگ"},
{"value":"301","label":"پیتزا و اغذیه فروشان"},
{"value":"302","label":"عکاسان، چاپخانه داران، لوازم التحریر و کتابفروشان"},
{"value":"303","label":"تانکرساز و کمدساز"},
{"value":"304","label":"فروشندگان لوازم الکترونیکی"},
{"value":"305","label":"فروشندگان لوازم الکتریکی"},
{"value":"306","label":"الکتروموتور و سیم پیچ"},
{"value":"307","label":"خیاطان و تولیدکنندگان پوشاک"},
{"value":"308","label":"فروشندگان ظروف (‌ چینی و بلور و آلومینیوم، ملامین )"},
{"value":"309","label":"ساندویچ و بستنی فروشان"},
{"value":"310","label":"پزندگان"},
{"value":"311","label":"پروفیل کاران آهن وآلومینیوم"},
{"value":"312","label":"طلا سازان و جواهر فروشان"},
{"value":"313","label":"کابینت سازان"},
{"value":"314","label":"فروشندگان لوازم یدکی و تعمیرکاران دوچرخه و موتور سیکلت"},
{"value":"315","label":"لوازم خانگی و طلا فروشان"},
{"value":"316","label":"فروشندگان لوازم الکتریکی و تعمیر کار لوازم خانگی"},
{"value":"317","label":"تعمیرکاران موتورسیکلت"},
{"value":"318","label":"سازندگان و فروشندگان مصنوعات فلزی"},
{"value":"319","label":"فروشندگان مصالح ساختمانی و معاملات ملکی"},
{"value":"320","label":"خیاطان، پوشاک، آرایشگران"},
{"value":"321","label":"قصابان و چلوکباب - کافه داران"},
{"value":"322","label":"لوازم بهداشتی و مصالح ساختمانی"},
{"value":"323","label":"تولیدی بلوک وتیرچه بلوک"},
{"value":"324","label":"لوازم خانگی و لوازم التحریر"},
{"value":"325","label":"قنادان و چلوکبابیها"},
{"value":"326","label":"فروشندگان میوه و تره بار و خواربار فروشان"},
{"value":"327","label":"الکتریکی و سیم پیچان"},
{"value":"328","label":"قنادان آبمیوه و بستنی"},
{"value":"329","label":"درودگران و چوب فروشان"},
{"value":"330","label":"لبنیات و سوپرمارکت"},
{"value":"331","label":"موزاییک سازان وخدمات ساختمان"},
{"value":"332","label":"برنج فروشان و علافان"},
{"value":"333","label":"فروشندگان چینی و بلور"},
{"value":"334","label":"چلوکباب و کباب"},
{"value":"335","label":"آلومینیوم کاران"},
{"value":"336","label":"آهنگران اتومبیل  و مکانیک"},
{"value":"337","label":"تابلوسازان و الکتریک"},
{"value":"338","label":"کابینت سازان و حلبی سازان"},
{"value":"339","label":"خیاطان و پیراهندوزان"},
{"value":"340","label":"درب و پنجره سازان آهنی"},
{"value":"341","label":"مطبوعات و فتوکپی"},
{"value":"342","label":"ماهی فروشان"},
{"value":"343","label":"موتورآلات کشاورزی و صنعتی"},
{"value":"344","label":"جوشکاران وآهنگران ودرب وپنجره سازان آهنی"},
{"value":"345","label":"کارواش ،‌ پنچرگیری و تعویض روغن"},
{"value":"346","label":"رایانه، ماشینهای اداری، کتاب و نوشت افزار"},
{"value":"347","label":"عکاسان و فتوکپی داران"},
{"value":"348","label":"قنادان واغذیه فروشان"},
{"value":"349","label":"مکانیک و تراشکاران"},
{"value":"350","label":"کفاشان و کفش فروشان"},
{"value":"351","label":"نمایشگاه اتومبیل، مشاورین املاک و جرثقیل"},
{"value":"352","label":"خواربار و لبنیات و موادغذایی"},
{"value":"353","label":"درب و پنجره سازان آلومینیومی و کابینت ساز"},
{"value":"354","label":"خیاطان مردانه، لحاف دوزان و خشک شویی"},
{"value":"355","label":"کتاب فروشان، لوازم التحریر، صنایع دستی و خرازان"},
{"value":"356","label":"طلا و جواهر، ساعت ساز، لوازم بهداشتی، صید و شکار و تابلو ساز"},
{"value":"357","label":"مرغ، ماهی و پلاژداران"},
{"value":"358","label":"تعمیرکاران چراغ و حلبی سازان"},
{"value":"359","label":"لوله کش گاز، خشکشویی، عاملین نفت"},
{"value":"360","label":"عکاسان و تابلوسازان"},
{"value":"361","label":"پارچه فروشان و طلا فروشان"},
{"value":"362","label":"الکتریکی و باطریساز"},
{"value":"363","label":"آهنگر  وصافکار اتومبیل"},
{"value":"364","label":"تولیدکنندگان و فروشندگان صنایع دستی"},
{"value":"365","label":"خرازی، پوشاک و پتو"},
{"value":"366","label":"فروشندگان لوازم بهداشتی و آرایشی"},
{"value":"367","label":"فروشندگان آبمیوه و بستنی و پالوده"},
{"value":"368","label":"الکتریکی و تعمیر لوازم خانگی و زرگری"},
{"value":"369","label":"تعمیرکاران ماشین آلات"},
{"value":"370","label":"پزندگان و مواد پروتیینی"},
{"value":"371","label":"اغذیه فروشان و رستوران داران"},
{"value":"372","label":"لوله کشی گاز"},
{"value":"373","label":"تعویض روغن"},
{"value":"374","label":"تعمیرکاران لوازم صوتی و تصویری، ماشین های اداری، رایانه و انفورماتیک"},
{"value":"375","label":"محلی دوزان"},
{"value":"376","label":"اتصالات ساختمانی"},
{"value":"377","label":"کبابی و جگرکی"},
{"value":"378","label":"علافان و فروشندگان خوراک دام و طیور"},
{"value":"379","label":"تزیینات داخلی ساختمان فروشنده فرش وموکت"},
{"value":"380","label":"خرازان، پلاستیک، لوازم خیاطی و لوازم بهداشتی"},
{"value":"381","label":"قصابان، پرندگان و مرغ فروشان"},
{"value":"382","label":"تعمیر کاران اتومبیل و باطریسازان"},
{"value":"383","label":"قصابان و فروشندگان مرغ و تخم مرغ"},
{"value":"384","label":"تعمیرکاران لوازم خانگی و طلا فروشان"},
{"value":"385","label":"درودگران و پروفیل کاران"},
{"value":"386","label":"نانوایان و علافان"},
{"value":"387","label":"فروشندگان لوازم التحریر و خدمات رایانه ای"},
{"value":"388","label":"تعمیرکاران اتومبیل، موتورسیکلت و تعویض روغن"},
{"value":"389","label":"زرگران و عکاسان و کامپیوتر"},
{"value":"390","label":"خیاطان و آرایشگران مردانه"},
{"value":"391","label":"نانوایان، قنادان، قصابان و مرغ فروشان"},
{"value":"392","label":"مشاورین املاک و لوازم التحریر"},
{"value":"393","label":"پارچه فروشان و فروشندگان فرش وموکت"},
{"value":"394","label":"خواربار فروشان سوپرمارکت و خشکبار"},
{"value":"395","label":"خرازی، میوه و تره بار و پلاستیک فروشان"},
{"value":"396","label":"عکاسان، خدمات و فروش کامپیوتر، بازی های رایانه ای، تکثیر اوراق و فروشندگان محصولات فرهنگی"},
{"value":"397","label":"خرازان، عطاران، مرغ و لبنیات فروش"},
{"value":"398","label":"بستنی، آبمیوه ، پالوده و حلوا ساز"},
{"value":"399","label":"فروشندگان لوازم التحریر و ماشینهای اداری"},
{"value":"400","label":"بازی های رایانه ای و تصویری و خدمات کامپیوتری"},
{"value":"401","label":"خیاطان و تودوزی"},
{"value":"402","label":"فروشندگان کیف و کفش و لوازم بهداشتی و ورزشی"},
{"value":"403","label":"ابزار آلات و لوله فروشان"},
{"value":"404","label":"خواربار فروشان و عطاری"},
{"value":"405","label":"زرگران و صنایع چاپی و عکاسی"},
{"value":"406","label":"قصابان و فروشندگان ماهی و پرنده"},
{"value":"407","label":"لوازم یدکی و ادوات کشاورزی و موتور سیکلت"},
{"value":"408","label":"پارچه فروشان، خیاطان و فروشندگان کیف و کفش"},
{"value":"409","label":"ادوات کشاورزی و درب و پنجره سازان"},
{"value":"410","label":"قنادان و آبمیوه گیران"},
{"value":"411","label":"جوشکاران ودرب وپنجره سازان آهنی"},
{"value":"412","label":"درود گران وموزاییک سازان"},
{"value":"413","label":"شیشه بران و فروشندگان شیشه و آیینه و تزیینات ساختمان"},
{"value":"414","label":"لوازم خانگی و پلاستیک فروشان"},
{"value":"415","label":"عکاسان، فتوکپی و نمایشگاه داران اتومبیل"},
{"value":"416","label":"تعمیرکاران اتومبیل سبک و سنگین، دوچرخه، موتورسیکلت، تعمیر ترمز و کلاج، گیربکس و دیفرانسیل"},
{"value":"417","label":"تعویض روغن، آپاراتی و باطریسازان"},
{"value":"418","label":"فروشندگان فرش، لوازم خانگی و تعمیرکاران"},
{"value":"419","label":"قناد، بستنی و فروشنده میوه و تره بار"},
{"value":"420","label":"اغذیه و چلوکباب"},
{"value":"421","label":"فروشندگان پوشاک و لوازم آرایشی و بهداشتی"},
{"value":"422","label":"درب و پنجره سازان آلومینیومی"},
{"value":"423","label":"چلوکبابی ها"},
{"value":"424","label":"الکترونیک و خدمات رایانه"},
{"value":"425","label":"خرازان و پلاستیک"},
{"value":"426","label":"فروشندگان آجیل و خشکبار و لبنیات"},
{"value":"427","label":"الکتریکی، عکاسان، رایانه و تعمیرات لوازم برقی"},
{"value":"428","label":"فروشندگان آبمیوه و بستنی و ساندویچ"},
{"value":"429","label":"فروشندگان و سازندگان طلا و جواهر و لوازم التحریر"},
{"value":"430","label":"پارچه فروشان، خرازی و فروشندگان کیف و کفش"},
{"value":"431","label":"فروشندگان لوازم یدکی و تاکسی تلفنی"},
{"value":"432","label":"شیشه بران و فروشندگان شیشه و آیینه و شیشه اتومبیل"},
{"value":"433","label":"ساندویچ فروشان و لبنیات"},
{"value":"434","label":"فروشگاه های عرضه محصولات فرهنگی"},
{"value":"435","label":"لوازم بهداشتی ساختمان و ابزارآلات"},
{"value":"436","label":"فروشندگان کتاب و لوازم التحریر وچاپخانه داران"},
{"value":"437","label":"خدمات تلفن همراه وتجهیزات مخابراتی"},
{"value":"438","label":"قصابان و مواد پروتیینی ( گوشتی)"},
{"value":"439","label":"خیاطان و پارچه فروشان"},
{"value":"440","label":"لوازم خانگی و خرازی و فرش و موکت"},
{"value":"441","label":"درود گران، شیشه بران ورنگ فروشان"},
{"value":"442","label":"نانوایان و غلات"},
{"value":"443","label":"فروشندگان لوازم التحریر و عکاسان"},
{"value":"444","label":"فروشندگان مواد پروتینی، میوه و گوشت"},
{"value":"445","label":"درب و پنجره سازان و مصالح ساختمانی"},
{"value":"446","label":"تزیینات داخلی ساختمان ورنگ فروشان"},
{"value":"447","label":"نمایشگاه اتومبیل و خدمات خودرویی"},
{"value":"448","label":"فروشندگان لاستیک و باطری"},
{"value":"449","label":"فروشندگان کیف، کفش، پارچه و پوشاک"},
{"value":"450","label":"بنکداران آجیل و خشکبار"},
{"value":"451","label":"هتل داران، میهمانپذیران و تالار جشنهای عروسی"},
{"value":"452","label":"الکتریکی و ابزار فروشان"},
{"value":"453","label":"نقاشان و خدمات رنگ آمیزی"},
{"value":"454","label":"فروشندگان لاستیک و باطری و تعویض روغن"},
{"value":"455","label":"خرازان، پوشاک، سیسمونی نوزاد و بهداشتی و آرایشی"},
{"value":"456","label":"خیاطان مردانه، پارچه فروشان، فرش و موکت و آرایشگران مردانه"},
{"value":"457","label":"لوازم الکتریکی و لوله کشی ساختمان"},
{"value":"458","label":"اغذیه فروشان، چلوکباب، قهوه خانه داران و قصابان"},
{"value":"459","label":"الکتریکی و شیشه بران"},
{"value":"460","label":"پارچه فروشان و تریکو فروشان"},
{"value":"461","label":"لوازم خانگی و مصنوعات چوبی"},
{"value":"462","label":"تعویض روغن و پنچرگیری صافکاران و نقاشان"},
{"value":"463","label":"نانوایان، قنادان و اغذیه فروشان"},
{"value":"464","label":"خواربارفروشان، لبنیات، عطار و علافان"},
{"value":"465","label":"خرازان، پوشاک و لوازم التحریر"},
{"value":"466","label":"درودگران و تعمیرکاران لوازم برقی"},
{"value":"467","label":"لوازم خانگی ، صوتی وتصویری و کرایه آنها"},
{"value":"468","label":"کفش و پوشاک و لوازم خرازی"},
{"value":"469","label":"جوشکاران و درودگران"},
{"value":"470","label":"قصابان و آلایش دامی"},
{"value":"471","label":"بازی های رایانه ای"},
{"value":"472","label":"مرغ فروشان"},
{"value":"473","label":"ادوات کشاورزی، حفاران و سموم آفات نباتی"},
{"value":"474","label":"بار فروشان میوه و تره بار، خشکبار و بنکداران"},
{"value":"475","label":"فروشندگان چینی و بلور و پلاستیک"},
{"value":"476","label":"تولیدکنندگان و تعمیرکاران لوازم برقی"},
{"value":"477","label":"خیاطان و بافندگان و شرکتهای خدماتی"},
{"value":"478","label":"مرغ و تخم مرغ"},
{"value":"479","label":"پارچه فروشان و دوزندگان پرده"},
{"value":"480","label":"حق العمل کاران"},
{"value":"481","label":"ابزار و یراق و رنگ و لوازم کشاورزی"},
{"value":"482","label":"مصالح ساختمانی، موزاییک سازان و فخاران"},
{"value":"483","label":"گل و میوه و تره بار"},
{"value":"484","label":"درودگران و آهنگران"},
{"value":"485","label":"آرایشگران و عکاسان"},
{"value":"486","label":"قصابان و میوه فروشان"},
{"value":"487","label":"فروشندگان پوشاک و طلا"},
{"value":"488","label":"آرایشگران، خیاطان و طلا فروشان"},
{"value":"489","label":"الکتریکی و نانوایان"},
{"value":"490","label":"تولید کنندگان وتعمیر کاران لوازم الکتریک"},
{"value":"491","label":"بلوک، موزاییک سازان و ورقکاران"},
{"value":"492","label":"چلوکبابی ها، هتل و مسافرخانه داران و قهوه خانه داران"},
{"value":"493","label":"فروشندگان پوشاک ، پارچه فروشان ، خرازی"},
{"value":"494","label":"فروشندگان فرش دستباف، موکت، تزیینات و گل فروشان"},
{"value":"495","label":"فروشندگان لوازم التحریر و عکاس و خدمات رایانه"},
{"value":"496","label":"جوشکاران"},
{"value":"497","label":"حق العمل کاران و خشکبار"},
{"value":"498","label":"فروشندگان لاستیک و پنچرگیری"},
{"value":"499","label":"الکتریکی و تزیینات ساختمان"},
{"value":"500","label":"فروشندگان و تعمیرکاران ساعت و عینک"},
{"value":"501","label":"ماشین ساز و فلز تراش"},
{"value":"502","label":"خدمات ارتباطی"},
{"value":"503","label":"فروشندگان کفش"},
{"value":"504","label":"گلگیرسازان و رادیاتورسازان"},
{"value":"505","label":"نقاشان اتومبیل و ساختمان"},
{"value":"506","label":"عایقهای رطوبتی ساختمان"},
{"value":"507","label":"فروشندگان تخته سه لا، فیبر و نیوپان"},
{"value":"508","label":"مرغ، تخم مرغ، پرنده و ماهی فروشان"},
{"value":"509","label":"هتل و رستوران"},
{"value":"510","label":"صافکاران و رادیاتورسازان"},
{"value":"511","label":"تراشکاران  و ریخته گران"},
{"value":"512","label":"آهنگران اتومبیل و میزان فرمان اتومبیل"},
{"value":"513","label":"فروشندگان و سازندگان طلا و جواهر و ساعت و خدمات رایانه ای"},
{"value":"514","label":"فروشندگان اغذیه و مواد پروتیینی"},
{"value":"515","label":"لوازم خانگی و مبل فروشان"},
{"value":"516","label":"هتلداران، چلوکباب و ساندویچ فروشان"},
{"value":"517","label":"درود گران ، شیشه بران ومبل سازان"},
{"value":"518","label":"رایانه، داده ورزی و ماشینهای اداری"},
{"value":"519","label":"خرازان ، لوازم آرایشی و خانگی"},
{"value":"520","label":"سنگ بر و سنگ تراش و نقاشان اتومبیل"},
{"value":"521","label":"آبنبات سازان و قندریزان"},
{"value":"522","label":"آهنگران"},
{"value":"523","label":"تزیینات داخلی ساختمان و مصالح ساختمانی"},
{"value":"524","label":"رنگ فروشان و نقاشان ساختمان"},
{"value":"525","label":"آهنگر و جلوبندی ساز"},
{"value":"526","label":"بنکداران و حق العمل کاران"},
{"value":"527","label":"عطاران، بذر و سموم فروش"},
{"value":"528","label":"قهوه خانه داران، جگرکی و کله پزی"},
{"value":"529","label":"فروشندگان لوازم بهداشتی و آرایشی ، خرازی و ورزشی"},
{"value":"530","label":"تعمیر کاران اتومبیل ، باطریسازان و پنچرگیری و تعویض روغن"},
{"value":"531","label":"گلگیر سازان و نقاشان"},
{"value":"532","label":"لوازم خانگی و خرازی و پلاستیک فروشان"},
{"value":"533","label":"گازرسانی و آبرسانی و ایزوگام"},
{"value":"534","label":"کفاشان و تعمیرکاران کفش"},
{"value":"535","label":"اغذیه فروشان و شیرینی پزان"},
{"value":"536","label":"مشاورین املاک و نمایشگاه اتومبیل و موتور"},
{"value":"537","label":"خطاطان و اتوکشان"},
{"value":"538","label":"ابزارآلات الکتریکی"},
{"value":"539","label":"شیشه بران و فروشندگان شیشه و آیینه و تاسیسات ساختمانی"},
{"value":"540","label":"کتاب فروشان و ناشران"},
{"value":"541","label":"فخاران و درودگران"},
{"value":"542","label":"آلومینیوم کاران و کمد و قابسازان"},
{"value":"543","label":"جوراب بافان و جوراب فروشان"},
{"value":"544","label":"چاقو سازان"},
{"value":"545","label":"سراجان و تشکدوزان اتومبیل"},
{"value":"546","label":"صفار و مسگر"},
{"value":"547","label":"صافکاران اتومبیل"},
{"value":"548","label":"ورقکاران"},
{"value":"549","label":"آرایشگران زنانه و فروشندگان لوازم بهداشتی و آرایشی و خرازی"},
{"value":"550","label":"خواربار فروشان و لبنیات و میوه و تره بار"},
{"value":"551","label":"فروشندگان سم"},
{"value":"552","label":"تعمیرکاران لوازم خانگی و اداری"},
{"value":"553","label":"فروشندگان فرش و پوشاک"},
{"value":"554","label":"آرایشگران وخدمات بهداشتی"},
{"value":"555","label":"قنادان، نانوایان و مواد غذایی"},
{"value":"556","label":"عکاسان، فیلمبرداران، تابلوسازان، فتوکپی و چاپخانه داران"},
{"value":"557","label":"قنادان و آجیل و خشکبار فروشان"},
{"value":"558","label":"چلوکبابی و مسافرخانه داران ( هتلداران)"},
{"value":"559","label":"سری دوزان پوشاک (تولیدی پوشاک)"},
{"value":"560","label":"قنادان ،‌نبات ریزان"},
{"value":"561","label":"فروشندگان پارچه، فرش،پتو،لحاف دوزان و خیاطان"},
{"value":"562","label":"قنادان، قصابان و اغذیه فروشان"},
{"value":"563","label":"تریکو بافان و زیرپیراهن بافان"},
{"value":"564","label":"قصابان و ساندویچ و چلوکبابی و مرغ و ماهی"},
{"value":"565","label":"شیشه بران و فروشندگان شیشه و آیینه ، نقاش و تابلوساز"},
{"value":"566","label":"لوازم بهداشتی ساختمان، لوله کش گاز، الکتریکی و ابزار فروشان"},
{"value":"567","label":"زیگزاگ دوزان"},
{"value":"568","label":"فروشندگان لوازم یدکی اتومبیل ، صافکاران و نقاشان"},
{"value":"569","label":"چلوکبابی و قهوه خانه داران"},
{"value":"570","label":"تریکوبافان و خشکشویی ها"},
{"value":"571","label":"صافکاران، رادیاتورساز و آهنگری"},
{"value":"572","label":"کتاب فروشان، لوازم التحریر و لوازم مهندسی"},
{"value":"573","label":"فروش و خدمات رایانه، ماشینهای اداری، موبایل و تلفن"},
{"value":"574","label":"فروشندگان لوازم خانگی و اداری"},
{"value":"575","label":"فروشندگان ادوات کشاورزی"},
{"value":"576","label":"تعویض روغن و باطریسازان"},
{"value":"577","label":"فروشندگان لوازم یدکی و مصالح ساختمانی"},
{"value":"578","label":"غذاخوریها ومیوه وتره بار"},
{"value":"579","label":"تعمیرکاران و فروشندگان موتورسیکلت"},
{"value":"580","label":"آهن آلات  و لوله و لوازم بهداشتی"},
{"value":"581","label":"کتاب فروشان"},
{"value":"582","label":"قصابی و کبابی"},
{"value":"583","label":"الکتریکی و طلا فروشان"},
{"value":"584","label":"تولیدکنندگان وتعمیرکاران یخچال، کولرگازی،تهویه مطبوع و لباسشویی"},
{"value":"585","label":"تریکو، پوشاک و لوازم بهداشتی"},
{"value":"586","label":"چلوکبابی، قصابی و مرغ فروشان"},
{"value":"587","label":"فروشندگان لوازم یدکی  موتور سیکلت"},
{"value":"588","label":"فروشندگان پوشاک و تریکو و پارچه"},
{"value":"589","label":"مصالح ساختمانی فلزی و غیر فلزی"},
{"value":"590","label":"فروشندگان ابزار کشاورزی و ساختمانی"},
{"value":"591","label":"کبابی و بریانی"},
{"value":"592","label":"موسسات حمل ونقل ( بار بین شهری )"},
{"value":"593","label":"فروشندگان کیف و کفش و لوازم وزرشی"},
{"value":"594","label":"فروشندگان لوازم خانگی، مبلمان، صوتی و تصویری، موسیقی و اداری"},
{"value":"595","label":"فروشندگان فرش وموکت، پتو و تزیینات قالی"},
{"value":"596","label":"فروشندگان میوه تره بار و علافان"},
{"value":"597","label":"عمده فروشان خواربار"},
{"value":"598","label":"تعمیرکاران اتومبیل و موتور سیکلت و باطریسازان"},
{"value":"599","label":"فروشندگان لاستیک ، کارواش ،‌ پنچرگیری و تعویض روغن"},
{"value":"600","label":"فروشندگان پسته"},
{"value":"601","label":"خیاطان زنانه و مردانه، تشک دوزان و خشکشویی"},
{"value":"602","label":"فروشندگان میوه تره بار و بارفروشان و گل فروشان"},
{"value":"603","label":"تراشکاران، آهنگر و صافکار و رادیاتورساز"},
{"value":"604","label":"کابینت سازان و شیشه بران و فروشندگان شیشه و آیینه"},
{"value":"605","label":"پنچرگیران"},
{"value":"606","label":"عکاسان، فیلمبرداران و لابراتوار چاپ"},
{"value":"607","label":"الکتریکی و جوشکاران"},
{"value":"608","label":"لوازم خانگی، خرازی و صوتی"},
{"value":"609","label":"قصابان و فروشندگان ماهی"},
{"value":"610","label":"فروشندگان لاستیک، دوچرخه و موتور"},
{"value":"611","label":"خیاطان، نساج و لحاف دوزان"},
{"value":"612","label":"تراشکاران و صافکاران"},
{"value":"613","label":"خیاطان و گلدوزان"},
{"value":"614","label":"صباغ، خامه فروشان و فرش فروشان"},
{"value":"615","label":"فروشندگان لوازم یدکی موتورسیکلت و دوچرخه"},
{"value":"616","label":"صافکاران و گلگیرسازان"},
{"value":"617","label":"کافه، قناد، اغذیه و لبنیات فروشان"},
{"value":"618","label":"الکترومکانیک"},
{"value":"619","label":"کانال سازان و حلبی سازان"},
{"value":"620","label":"عمده فروشان برنج و حبوبات"},
{"value":"621","label":"فروشندگان لوازم طبی و آزماشیگاهی و خوراک کودک"},
{"value":"622","label":"فروشندگان لوازم ورزشی"},
{"value":"623","label":"عکاسان و ساعت فروشان"},
{"value":"624","label":"زرگران، عکاسان و آرایشگران"},
{"value":"625","label":"فروشنده لوازم یدکی، نمایشگاه اتومبیل، لاستیک و روغن فروشان"},
{"value":"626","label":"قصابان، نانوایان و ساندویچ فروشان"},
{"value":"627","label":"سفال و سرامیک"},
{"value":"628","label":"لنت کوبان"},
{"value":"629","label":"آهنگران اتومبیل  و کمک فنرسازان"},
{"value":"630","label":"فروشندگان لوازم یدکی اتومبیل سبک"},
{"value":"631","label":"فروشندگان کیف و کفش،فرش و موکت"},
{"value":"632","label":"الکتریکی، طلا و خدمات کامپیوتری"},
{"value":"633","label":"فروشندگان پوشاک، کیف وکفش، طلا و لوازم خانگی"},
{"value":"634","label":"فروشندگان رنگ ابزار و یراق و آهن آلات"},
{"value":"635","label":"پارچه فروشان و فروشندگان لوازم بهداشتی و آرایشی"},
{"value":"636","label":"خرازان و طلا فروشان"},
{"value":"637","label":"خواربارفروشان، قصابان و غذاخوری ها"},
{"value":"638","label":"صافکاران، نقاشان و تعویض روغن"},
{"value":"639","label":"خیاطان، خشکشویی، آرایشگران"},
{"value":"640","label":"چلوکباب، اغذیه، کافه، قصابی، مرغ و تخم مرغ، ماهی و میوه وتره بار"},
{"value":"641","label":"تزیینات داخلی ساختمان ،فرش فروشان ولوازم خانگی"},
{"value":"642","label":"قصابان و مرغ و میوه فروشان"},
{"value":"643","label":"خیاطان، خشکشویی و کفاشان"},
{"value":"644","label":"قصابان و پزندگان"},
{"value":"645","label":"خطاطان و نقاشان"},
{"value":"646","label":"های مجازی(شهرداری - بخشداری)"},
{"value":"647","label":"فروشندگان چینی و بلور و استیل"},
{"value":"648","label":"خرازی و لوازم وزرشی"},
{"value":"649","label":"قنادان، بستنی و خشکبار"},
{"value":"650","label":"فروشندگان لوازم پزشکی وخنچه عقد"},
{"value":"651","label":"فروشندگان لوازم  بهداشتی و آرایشی ، گلفروشان"},
{"value":"652","label":"خرازان و کاموا فروشان"},
{"value":"653","label":"دستگاه های مخابراتی، ارتباطی و لوازم جانبی"},
{"value":"654","label":"تولید کنندگان و فروشندگان نان های حجیم و نیمه حجیم ( نان فانتزی )"},
{"value":"655","label":"قصابان و مرغ فروشان و اغذیه فروشان"},
{"value":"656","label":"ندافان و پیراهن دوزان"},
{"value":"657","label":"مصالح ساختمانی، شیشه بران و بلوک سازان"},
{"value":"658","label":"کاموا فروشان"},
{"value":"659","label":"تجهیزات پزشکی و عینک سازان"},
{"value":"660","label":"لوازم صیادی"},
{"value":"661","label":"فروشندگان آهن و سیمان"},
{"value":"662","label":"برنج فروشان"},
{"value":"663","label":"مشاور املاک و اتومبیل و معاملات چای و چای ریزان"},
{"value":"664","label":"فروشندگان لوازم یدکی اتومبیل، موتور، دوچرخه و نمایشگاه اتومبیل"},
{"value":"665","label":"فروشندگان لوازم التحریر و بهداشتی"},
{"value":"666","label":"تعمیرکاران اتومبیل و دوچرخه،تراشکاران، تعویض روغن و سرویس کاران"},
{"value":"667","label":"خرازان، پوشاک و مطبوعات"},
{"value":"668","label":"بنگاه داران وانت بار"},
{"value":"669","label":"گونی دوزان"},
{"value":"670","label":"سقط فروشان"},
{"value":"671","label":"فروشندگان نفت و مواد نفتی"},
{"value":"672","label":"خرازان، کیف و کفش فروشان"},
{"value":"673","label":"پارچه فروشان و لوازم التحریر"},
{"value":"674","label":"خیاطان و لحافدوزان"},
{"value":"675","label":"سنگ، بلوک زنی و درودگری"},
{"value":"676","label":"علافان و لوازم التحریر"},
{"value":"677","label":"زعفران و خشکبار فروشان"},
{"value":"678","label":"درب و پنجره سازان و آهن فروشان"},
{"value":"679","label":"درودگران و آلومینیوم کاران"},
{"value":"680","label":"عکاسان، خدمات رایانه و طلا و ساعت"},
{"value":"681","label":"پوشاک ،پارچه فروشان وخیاطان"},
{"value":"682","label":"فروشندگان کیف و کفش و لوازم التحریر"},
{"value":"683","label":"زعفران فروشان"},
{"value":"684","label":"تشکدوزان اتومبیل و صافکاران"},
{"value":"685","label":"فروشندگان فرش و پارچه و پوشاک"},
{"value":"686","label":"ورقکاران و آهنگران"},
{"value":"687","label":"بنایان و معماران"},
{"value":"688","label":"تولید و فروش استیل و برنج"},
{"value":"689","label":"تولیدکنندگان و فروشندگان کالاهای کشباف و جوراب باف"},
{"value":"690","label":"مبلمان ساز و مبلمان فروش"},
{"value":"691","label":"سازندگان و فروشندگان لوازم مسی"},
{"value":"692","label":"تولیدکنندگان مصنوعات مقوایی"},
{"value":"693","label":"چادردوزان"},
{"value":"694","label":"تعمیر کاران وفروشندگان  چرخهای خیاطی و بافندگی"},
{"value":"695","label":"تعمیر کاران اتومبیل سبک"},
{"value":"696","label":"تعمیرکار ان اتومبیل سنگین"},
{"value":"697","label":"کوره پز"},
{"value":"698","label":"تولیدکنندگان و تعمیرکاران سیم پیچ، الکتروموتور و ژنراتور"},
{"value":"699","label":"نقاشان اتومبیل"},
{"value":"700","label":"فروشندگان محصولات زیتون"},
{"value":"701","label":"لوازم یدکی و ابزار و یراق فروشان"},
{"value":"702","label":"جوشکاران، آلومینیوم کاران و تاسیسات حرارتی"},
{"value":"703","label":"مشاورین املاک و نمایشگاه اتومبیل و پارکینگ داران"},
{"value":"704","label":"پیله و ابریشم کشان"},
{"value":"705","label":"چاپخانه، تایپ و تکثیر"},
{"value":"706","label":"فخاران، موزاییک سازان و ایزوگام"},
{"value":"707","label":"آیینه و لوستر"},
{"value":"708","label":"خدمات رایانه و ماشینهای اداری"},
{"value":"709","label":"درودگران و کابینت سازان چوبی"},
{"value":"710","label":"بلوک زنان و عایقهای رطوبتی"},
{"value":"711","label":"شرکتهای حمل و نقل و جرثقیل و انبارداری"},
{"value":"712","label":"ساعت، عینک و لوازم طبی"},
{"value":"713","label":"تعمیرکاران موتور سیکلت و دوچرخه و باطریسازان"},
{"value":"714","label":"مصنوعات فلزی و فلز تراش"},
{"value":"715","label":"تولید کنندگان و تعمیر کاران الکترو نیک و الکترو تکنیک"},
{"value":"716","label":"تهیه کنندگان و فروشندگان کلاه و لوازم ایمنی"},
{"value":"717","label":"فروشندگان فرش و موکت و مبلمان"},
{"value":"718","label":"فروشندگان لوازم التحریر و محصولات فرهنگی"},
{"value":"719","label":"فروشندگان لوازم یدکی اتومبیل و مشاورین املاک"},
{"value":"720","label":"تولیدکنندگان و فروشندگان مصنوعات سیمانی و لوازم فلزی"},
{"value":"721","label":"سازندگان و فروشندگان ظروف آلومینیوم"},
{"value":"722","label":"نانوایان و فروشنده میوه و تره بار"},
{"value":"723","label":"فروشندگان میوه و تره بار و نهاده های کشاورزی"},
{"value":"724","label":"کامیون، جرثقیل و موسسات اتومبیل کرایه"},
{"value":"725","label":"فروشندگان فرش و موکت و پرده"},
{"value":"726","label":"فروشنده مصالح ساختمانی وخدمات عایقهای رطوبتی ساختمان"},
{"value":"727","label":"شیشه فروشان وآلومینیوم کاران"},
{"value":"728","label":"الیاف و آب شیرین و سوخت و گرمابه داران"},
{"value":"729","label":"چاپخانه داران و کتابفروشان"},
{"value":"730","label":"فروشندگان و سازندگان طلا و جواهر و ساعت و خرازان"},
{"value":"731","label":"فروشندگان میوه و تره بار و آرد گندم"},
{"value":"732","label":"الکتریکی و عکاسان"},
{"value":"733","label":"درب و پنجره سازان وتراشکاران"},
{"value":"734","label":"آهن فروشان، ابزارآلات"},
{"value":"735","label":"دفاتر آژانسهای تاکسی تلفنی و وانت بار داران"},
{"value":"736","label":"تعمیرکاران اتومبیل و تنظیم فرمان"},
{"value":"737","label":"تابلوسازان و مهر و پلاک"},
{"value":"738","label":"کفش، تشک دوزان  و چادر دوزان"},
{"value":"739","label":"غلات، حبوبات و سم فروشان"},
{"value":"740","label":"آهنگران و تانکرسازان"},
{"value":"741","label":"خامه فروش و رنگرز"},
{"value":"742","label":"مصالح ساختمانی، جوشکاران"},
{"value":"743","label":"لوازم برقی و کامپیوتر"},
{"value":"744","label":"خدمات گازرسانی، لوله و لوازم بهداشتی و درودگران"},
{"value":"745","label":"بنگاه داران، باسکول، وانت تلفنی، تاکسی تلفنی و نمایشگاه اتومبیل"},
{"value":"746","label":"فروشندگان ظروف چینی، پلاستیک، یکبارمصرف و ظروف کرایه"},
{"value":"747","label":"سم، بذر، کود وگل"},
{"value":"748","label":"قنادان و پزندگان"},
{"value":"749","label":"جوشکاران و کابینت سازان"},
{"value":"750","label":"آلومینیوم کار و حلبی ساز"},
{"value":"751","label":"خیاطان،آرایشگران، گرمابه و خشکشویی ها"},
{"value":"752","label":"خشکشویی ،‌لباس شویی و گرمابه داران"},
{"value":"753","label":"بیسکویت و شکلات"},
{"value":"754","label":"کاموا - روسری - حوله و کالای ورزشی"},
{"value":"755","label":"قصابان و فروشندگان  مرغ ، ساندویچ و چلوکباب"},
{"value":"756","label":"صافکاران، اتاقساز، داشبوردساز"},
{"value":"757","label":"تعمیرکاران  اتومبیل  و لنت کوبان"},
{"value":"758","label":"سنگبر و موزاییک ساز"},
{"value":"759","label":"خیاطان و فروشندگان پوشاک"},
{"value":"760","label":"عطاران، سقط و میوه فروشان"},
{"value":"761","label":"جوشکاران و آهنگران"},
{"value":"762","label":"شیشه بران و فروشندگان شیشه و آیینه و کلید سازان"},
{"value":"763","label":"هتلداران و مسافرخانه داران"},
{"value":"764","label":"فروشندگان مواد پروتیینی(گوشتی)"},
{"value":"765","label":"نخود پزان"},
{"value":"766","label":"فروشندگان مرغ و میوه و ماهی"},
{"value":"767","label":"نمایشگاه کامیون داران"},
{"value":"768","label":"مصالح ساختمانی، آهن و رنگ فروشان"},
{"value":"769","label":"تراشکاران و دینام پیچان"},
{"value":"770","label":"فروشندگان لوازم الکتریکی و تعمیر و فروش تلفن"},
{"value":"771","label":"عکاسان و خطاطان"},
{"value":"772","label":"کتابفروشان و مشاوران املاک و خودرو"},
{"value":"773","label":"تراشکاران ادوات کشاورزی"},
{"value":"774","label":"فروشندگان لوازم التحریر و خرازی و کفاش"},
{"value":"775","label":"شرکتهای مسافربری و جرثقیل"},
{"value":"776","label":"قصاب و موادپروتیینی و ساندوچی و کبابی"},
{"value":"777","label":"فروشندگان چینی و بلور و استیل و لوازم بهداشتی"},
{"value":"778","label":"تهیه کنندگان و فروشندگان عرقیات معطر، آبلیمو و ترشیجات"},
{"value":"779","label":"تعمیرکاران و فروشندگان تلفن و لوازم جانبی"},
{"value":"780","label":"چادر و خیمه دوز"},
{"value":"781","label":"قنادان و یوخه پزان"},
{"value":"782","label":"خواربار، خشکبار و بنکداران مواد غذایی"},
{"value":"783","label":"درب و پنجره سازان آهنی و آهنکاران ساختمانی"},
{"value":"784","label":"پتو فروشان و فرآورد های اسفنجی"},
{"value":"785","label":"فروشندگان سموم دفع آفات نباتی و خانگی و گل و بذر و داروهای دامی و طیور"},
{"value":"786","label":"دارندگان کارگاه های ظهور فیلم، چاپ و تکثیر عکس"},
{"value":"787","label":"الکتریکی، برقکار، لوستر فروش و برق صنعتی"},
{"value":"788","label":"خاتم ساز و خاتم فروشی"},
{"value":"789","label":"صافکاران، گلگیرساز و نقاشان اتومبیل"},
{"value":"790","label":"تعمیرکاران لوازم صوتی و تصویری و عکاسان"},
{"value":"791","label":"جرثقیل دارن"},
{"value":"792","label":"نقاشان و تشکدوزان اتومبیل"},
{"value":"793","label":"ساندویچ فروشان، چلوکباب و قصابان"},
{"value":"794","label":"آسیابدار و علاف"},
{"value":"795","label":"سازندگان و توزیع کنندگان ظروف ملامین و اسباب بازی فروشان"},
{"value":"796","label":"ابزارآلات و آهن فروشان"},
{"value":"797","label":"باطریسازان و باطری فروشان و سیم پیچان"},
{"value":"798","label":"لوازم الکتریکی، لوله و اتصالات"},
{"value":"799","label":"علافان، میوه و گل فروشان و سموم دفع آفات نباتی"},
{"value":"800","label":"اسفنج و پارچه فروشان"},
{"value":"801","label":"آرایشی و بهداشتی و گالری لباس عروس"},
{"value":"802","label":"فروشندگان لوازم التحریر و نوار فروشان"},
{"value":"803","label":"تعمیرات رادیو، تلویزیون و سیم پیچی"},
{"value":"804","label":"تراشکاران و لوله کشی آب و گاز"},
{"value":"805","label":"لوازم خانگی و سمساری"},
{"value":"806","label":"پارچه فروشان و تزیینات پرده و گل"},
{"value":"807","label":"آسیابدار و بارفروش"},
{"value":"808","label":"هتلداران و بنگاه و خشکشویی"},
{"value":"809","label":"تراشکاران، صافکاران  و نقاشان"},
{"value":"810","label":"دارندگان اتوسرویس و توقفگاه و پارکینگ"},
{"value":"811","label":"تولید پلاستیک"},
{"value":"812","label":"آلومینیوم کاران و قفل و کلید سازان"},
{"value":"813","label":"فروشندگان پوشاک، لوازم وزرشی، منسوجات حوله ای و کاموا"},
{"value":"814","label":"خرده فروشی مواد غذایی"},
{"value":"815","label":"صافکاران، نقاشان، رادیاتورسازان، صنایع فلزی و کابینت سازان"},
{"value":"816","label":"تعویض روغن، تعمیرکار و فروشندگان لوازم موتور سیکلت"},
{"value":"817","label":"فروشندگان آجیل و خشکبار و غلات"},
{"value":"818","label":"فروشندگان دام و طیور"},
{"value":"819","label":"عکاسان، عینک سازان و ساعت"},
{"value":"820","label":"تانکرساز و ورقکاران"},
{"value":"821","label":"جلوبندی و آپاراتی و آهنگری اتومبیل"},
{"value":"822","label":"تراشکاران و باطری سازان و کلید سازان"},
{"value":"823","label":"کافه، رستوران، کبابی و ساندویچی"},
{"value":"824","label":"لحاف و تشک دوزان"},
{"value":"825","label":"اغذیه و تره بار"},
{"value":"826","label":"مواد شیمیایی"},
{"value":"827","label":"تولید کنندگان وفروشندگان لوازم الکتریک"},
{"value":"828","label":"درودگران و مصالح ساختمانی و شیشه فروشان"},
{"value":"829","label":"تولیدکنندگان فرش دستباف، مصالح فرش، فرش ماشینی و موکت فروشان"},
{"value":"830","label":"فروشندگان پوشاک و لوازم خانگی"},
{"value":"831","label":"تراشکاران و آهنگران"},
{"value":"832","label":"تعمیر کاران اتومبیل و موتور آلات کشاورزی"},
{"value":"833","label":"شیشه بران و فروشندگان شیشه و آیینه و آلومینیوم ساز و پنچرگیری"},
{"value":"834","label":"حلوا وسوهان پزان"},
{"value":"835","label":"گچ پزان"},
{"value":"836","label":"نان برنجی و کاک پزان"},
{"value":"837","label":"کرایه دهندگان ظروف و چادر"},
{"value":"838","label":"فروشندگان سموم و لوازم کشاورزی"},
{"value":"839","label":"لوله و تزیینات ساختمان"},
{"value":"840","label":"صنایع برودتی وتهویه مطبوع"},
{"value":"841","label":"چادر دوزان و دوزندگان اتومبیل"},
{"value":"842","label":"فروشندگان میوه و تره بار و مواد پروتیینی"},
{"value":"843","label":"فروشندگان پوشاک ، پارچه  و طلا"},
{"value":"844","label":"لوازم التحریر و خدمات کامپیوتری و مشاورین املاک"},
{"value":"845","label":"کبابی و رستوران داران"},
{"value":"846","label":"خیاطان و تزیینات و موکت"},
{"value":"847","label":"نانوایان، قنادان، آسیابدارن، آبنبات ریزان"},
{"value":"848","label":"پیراهن دوزان، خشکشویی و لباسشویی"},
{"value":"849","label":"کتاب فروشان و لوازم التحریر و صحافی"},
{"value":"850","label":"فروشندگان و تولیدکنندگان مصالح ساختمانی"},
{"value":"851","label":"خواربارفروشان و سوپر مارکت"},
{"value":"852","label":"زرگران، تابلوسازان و عکاسان و خیاطان"},
{"value":"853","label":"گل دوزان و صنایع دستی"},
{"value":"854","label":"فروشنده مواد اولیه فرش"},
{"value":"855","label":"فروشندگان پوشاک و پارچه و تزیینات و پرده"},
{"value":"856","label":"عسل فروشان"},
{"value":"857","label":"قصابان بنگاه داران و خدمات عمومی"},
{"value":"858","label":"خرازان، گل و پلاسیتک فروشان"},
{"value":"859","label":"نصب کنندگان داربست فلزی"},
{"value":"860","label":"کتاب فروشان و مشاورین املاک"},
{"value":"861","label":"لودر ،کمپرسی وکوره داران"},
{"value":"862","label":"همگن"},
{"value":"863","label":"مشاورین املاک، اتومبیل، موسسات اتومبیل کرایه"},
{"value":"864","label":"قنادان وبار فروشان میوه وتره بار"},
{"value":"865","label":"فروشندگان پیچ و مهره"},
{"value":"866","label":"بنگاه داران و خدمات عمومی"},
{"value":"867","label":"فروشندگان لوازم بهداشتی و آرایشی و گرمابه داران"},
{"value":"868","label":"فروشندگان پلاسکو و ملامین"},
{"value":"869","label":"مصالح ساختمانی، الکتریکی و املاک و شیشه گران"},
{"value":"870","label":"سیمان، گچ و سنگ فروشان"},
{"value":"871","label":"نمایشگاه اتومبیل، بنگاه معاملات، مصالح ساختمانی، ابزار و یراق و تیرچه بلوک"},
{"value":"872","label":"فروشندگان پوشاک، کیف و کفش، آرایشی و بهداشتی و لوازم التحریر"},
{"value":"873","label":"قنادان ، نانوایان، عکاسان"},
{"value":"874","label":"قصابان و موادپروتیینی و غذاخوری"},
{"value":"875","label":"مصالح ساختمانی، رنگ و پلاستیک و مشاورین املاک"},
{"value":"876","label":"خدمات بهداشتی و خیاطی"},
{"value":"877","label":"مشاورین املاک و علوفه و دام و طیور"},
{"value":"878","label":"فروشندگان گوشت گوسفندی و ماهی"},
{"value":"879","label":"فروشندگان رنگ ، میخ ،قفل و لولا"},
{"value":"880","label":"فروشندگان پوشاک، خرازی، لوازم التحریر، بهداشتی و آرایشی، کاموا فروشی، گل فروشی، لوازم ورزشی"},
{"value":"881","label":"صافکار، نقاش اتومبیل، آپاراتی، رادیاتورساز، اگزوزساز، باطریساز و سیم کش، آهنگری و جلوبندی"},
{"value":"882","label":"الکتریکی ، طلا و ساعت، عکاسان و فیلمبرداران و تعمیر لوازم صوتی و تصویری"},
{"value":"883","label":"تشکدوزان  اتومبیل و لحاف دوزان"},
{"value":"884","label":"عطار سقط فروش وبرنج فروش"},
{"value":"885","label":"چکش کار وریخته گر"},
{"value":"886","label":"دفاتر فنی وپیمانکاران ساختمان"},
{"value":"887","label":"خدمات رایانه و عکاسان و چاپخانه داران، مهرساز و جعبه ساز"},
{"value":"888","label":"میوه وتره بار ،قصاب ،اغذیه فروشان ، رستورانداران ، مجتمع اقامتی و فر آورده های گوشتی"},
{"value":"889","label":"قهوه خانه داران ، کبابی و اغذیه فروشان"},
{"value":"890","label":"وسایل سنگین راه سازی وچرثقیل داران"},
{"value":"891","label":"خرازی و خواربار فروشان"},
{"value":"892","label":"تولید کنندگان قطعات لاستیکی"},
{"value":"893","label":"قنادان ، ساندویچ فروشان و هتلداران"},
{"value":"894","label":"تعمیرکاران وسایط نقلیه موتوری، تعویض روغن و پنچرگیری و جوشکاری"},
{"value":"895","label":"قصابان و مرغ پرکنده فروشان و میوه و تره بار فروشان و کافه داران"},
{"value":"896","label":"لوازم خانگی، فرش و موکت، قماش، خرازی، پرده و پتو"},
{"value":"897","label":"کالای ملوانی"},
{"value":"898","label":"گرمابه داران و بنگاه های معاملاتی"},
{"value":"899","label":"فروشندگان و سازندگان طلا و جواهر ،عکاسان و نانوایان"},
{"value":"900","label":"تولید لپه"},
{"value":"901","label":"بازیافت ضایعات فلز و پلاستیک"},
{"value":"902","label":"تولید کنندگان و فروشندگان انجیر"},
{"value":"903","label":"گرمابه داران"},
{"value":"904","label":"حوله بافان"},
{"value":"905","label":"بافندگان پارچه"},
{"value":"906","label":"نانوایان وقصابان"},
{"value":"907","label":"دکه داران"},
{"value":"908","label":"فرش دستباف وصنایع دستی"},
{"value":"909","label":"تعمیرکاران لوازم خانگی و کامپیوتر"},
{"value":"910","label":"فروشندگان سیمان"},
{"value":"911","label":"رستوران های سنتی وییلاقی"},
{"value":"912","label":"لوازم یدکی، لاستیک و مشاورین املاک و نمایشگاه و آژانس مسافرتی"},
{"value":"913","label":"تابلوسازان و نقشه برداران"},
{"value":"914","label":"فروشندگان و سازندگان طلا و جواهر ،ساعت و عینک و فروشندگان فرش و موکت"},
{"value":"915","label":"فروشندگان آرد و غلات"},
{"value":"916","label":"دواتگران"},
{"value":"917","label":"موسسات حمل و نقل بار و مسافر"},
{"value":"918","label":"فناوران رایانه"},
{"value":"919","label":"مصنوعات هنری"},
{"value":"920","label":"کلیشه و لیتوگراف، مهر و چاپ پلاک و اسکرین"},
{"value":"921","label":"فروشندگان لاستیک و روغن اتومبیل"},
{"value":"922","label":"تریکو و کشباف"},
{"value":"923","label":"فیروزه تراشان"},
{"value":"924","label":"لوله کشان آب"},
{"value":"925","label":"پزندگان و چایخانه داران"},
{"value":"926","label":"عمده فروش پارچه"},
{"value":"927","label":"فروشندگان لوازم یدکی، مصنوعات، نفت، گاز و الکتریک"},
{"value":"928","label":"هتل آپارتمان داران"},
{"value":"929","label":"گل فروشان و سموم دفع آفات نباتی"},
{"value":"930","label":"پتو فروشان"},
{"value":"931","label":"فروشندگان وتولید کنندگان تریکو وکشباف"},
{"value":"932","label":"فروشندگان گیاهان دارویی"},
{"value":"933","label":"خیاطان مردانه،  گرمابه داران و خشکشویی"},
{"value":"934","label":"کانال سازان  و کابینت ساز و مسگر و کلید ساز"},
{"value":"935","label":"فروشندگان آجیل و خشکبار و عطار"},
{"value":"936","label":"خدمات رایانه ای، بازی های تصویری، کافی نت ، عکاسی و فتوکپی و چاپخانه"}
]
